add_more_distance_into_proeperty_x_lugar.py
load_templates.py
main.py
pr.py
pr2.py
pr_acrecer.py
pr_slug.py
pr_subscription.py
scripts.py
orion/__init__.py
orion/create_tables.py
orion/definition_ids.py
orion/tools.py
orion/acrecer/__init__.py
orion/acrecer/acrecer.py
orion/acrecer/etl_acrecer.py
orion/acrecer/permitted_neighborhoods.py
orion/acrecer/permmited_cities.py
orion/config/__init__.py
orion/config/settings.py
orion/config/verify_env_files.py
orion/databases/__init__.py
orion/databases/config_db_bellatrix.py
orion/databases/config_db_empatia.py
orion/databases/db_bellatrix/__init__.py
orion/databases/db_bellatrix/models/model_acrecer.py
orion/databases/db_bellatrix/models/model_mls.py
orion/databases/db_bellatrix/models/model_simi.py
orion/databases/db_bellatrix/models/model_softin.py
orion/databases/db_bellatrix/repositories/query_acrecer.py
orion/databases/db_bellatrix/repositories/querys_base_bellatix.py
orion/databases/db_bellatrix/repositories/querys_mls.py
orion/databases/db_bellatrix/repositories/querys_simi.py
orion/databases/db_bellatrix/repositories/querys_softin.py
orion/databases/db_empatia/__init__.py
orion/databases/db_empatia/utils.py
orion/databases/db_empatia/models/model_leech.py
orion/databases/db_empatia/models/model_searcher.py
orion/databases/db_empatia/models/models_sectors.py
orion/databases/db_empatia/repositories/querys_base_empatia.py
orion/databases/db_empatia/repositories/querys_leech.py
orion/databases/db_empatia/repositories/querys_searcher.py
orion/databases/db_empatia/repositories/repository_for_geospatial_calculations.py
orion/databases/db_empatia/repositories/repository_for_loading_to_sectors.py
orion/databases/db_empatia/repositories/repository_sectors.py
orion/databases/db_empatia/sp/__init__.py
orion/databases/db_empatia/sp/sp.py
orion/georeferencer/__init__.py
orion/georeferencer/get_property_sectors.py
orion/georeferencer/get_sectors.py
orion/georeferencer/get_surname_sector.py
orion/georeferencer/processing_data.py
lagencia_orion-1.0.31.dist-info/METADATA
lagencia_orion-1.0.31.dist-info/WHEEL
lagencia_orion-1.0.31.dist-info/top_level.txt
lagencia_orion-1.0.31.dist-info/RECORD
