Metadata-Version: 2.4
Name: LAgencia-orion
Version: 1.0.31
Summary: Add your description here
Requires-Python: >=3.11
Requires-Dist: aiohttp==3.10.5
Requires-Dist: alembic==1.13.2
Requires-Dist: geoalchemy2==0.18.0
Requires-Dist: geopandas==1.1.1
Requires-Dist: httpx==0.28.1
Requires-Dist: invoke==2.2.0
Requires-Dist: loguru==0.7.3
Requires-Dist: myst-parser>=4.0.1
Requires-Dist: openpyxl>=3.1.5
Requires-Dist: pandas==2.2
Requires-Dist: pydantic==2.8.2
Requires-Dist: pydantic-settings==2.11.0
Requires-Dist: pymysql==1.1.2
Requires-Dist: pytest>=9.0.1
Requires-Dist: pytest-asyncio>=1.3.0
Requires-Dist: python-slugify>=8.0.4
Requires-Dist: sqlalchemy==1.4.53
Requires-Dist: sqlalchemy2-stubs>=0.0.2a38
